optimade_mcp_server/__init__.py
optimade_mcp_server/main.py
optimade_mcp_server/config/optimade_config.json
optimade_mcp_server-0.1.2.dist-info/licenses/LICENSE
optimade_mcp_server-0.1.2.dist-info/METADATA
optimade_mcp_server-0.1.2.dist-info/WHEEL
optimade_mcp_server-0.1.2.dist-info/entry_points.txt
optimade_mcp_server-0.1.2.dist-info/top_level.txt
optimade_mcp_server-0.1.2.dist-info/RECORD
