Metadata-Version: 2.4
Name: optimade-mcp-server
Version: 0.1.2
Summary: A MCP-compatible OPTIMADE server with configurable filters and endpoints.
Author-email: lsb <763568748@qq.com>
Requires-Python: >=3.10
License-File: LICENSE
Requires-Dist: httpx>=0.28.1
Requires-Dist: mcp[cli]>=1.9.4
Requires-Dist: optimade[http-client]>=1.2.4
Requires-Dist: python-dotenv>=1.0.1
Requires-Dist: rich<14.dev0,>=13.0
Dynamic: license-file
